Metadata-Version: 2.1
Name: pyxdh
Version: 0.0.7
Summary: Document and code of python and PySCF approach XYG3 type of density functional realization
Author-email: ajz34 <ajz34@outlook.com>
Project-URL: Homepage, https://github.com/ajz34/Py_xDH
Project-URL: Documentation, https://py-xdh.rtfd.io
Classifier: Programming Language :: Python :: 3
Classifier: License :: OSI Approved :: GNU General Public License v3 (GPLv3)
Classifier: Operating System :: POSIX :: Linux
Requires-Python: <3.9,>=3.8
License-File: LICENSE
Requires-Dist: pyscf ==1.7.5
Requires-Dist: h5py ==3.0
Requires-Dist: scipy ==1.4.1
Requires-Dist: numpy ==1.18
Requires-Dist: opt-einsum
Requires-Dist: jupyter
Requires-Dist: sphinx
Requires-Dist: nbsphinx
Requires-Dist: pyberny
Requires-Dist: sphinx-rtd-theme
Requires-Dist: sphinxcontrib-bibtex
Requires-Dist: jupyter-contrib-nbextensions
Requires-Dist: pandoc
Requires-Dist: matplotlib
Requires-Dist: docopt
Requires-Dist: codecov
Requires-Dist: pytest-cov
